CliFunction.py
clifunction-0.2.4.dist-info/METADATA
clifunction-0.2.4.dist-info/WHEEL
clifunction-0.2.4.dist-info/licenses/LICENSE
clifunction-0.2.4.dist-info/RECORD
