Metadata-Version: 2.1
Name: clifunction
Version: 0.2.4
Summary: Build a fully featured CLI for your python project with minium effort
Project-URL: Homepage, https://github.com/Isaak-Malers/clifunction
Project-URL: Bug Tracker, https://github.com/Isaak-Malers/clifunction/issues
Project-URL: Documentation, https://isaak-malers.github.io/clifunction/
Author-email: Isaak Malers <isaak.malers+clifunction@gmail.com>
License-File: LICENSE
Classifier: License :: OSI Approved :: MIT License
Classifier: Operating System :: OS Independent
Classifier: Programming Language :: Python :: 3
Requires-Python: >=3.8
